LightWave2D/__init__.py
LightWave2D/_version.py
LightWave2D/binary/__init__.py
LightWave2D/binary/interface_config.cp310-win_amd64.pyd
LightWave2D/binary/interface_config.cp311-win_amd64.pyd
LightWave2D/binary/interface_config.cp312-win_amd64.pyd
LightWave2D/binary/interface_field_set.cp310-win_amd64.pyd
LightWave2D/binary/interface_field_set.cp311-win_amd64.pyd
LightWave2D/binary/interface_field_set.cp312-win_amd64.pyd
LightWave2D/binary/interface_mesh_set.cp310-win_amd64.pyd
LightWave2D/binary/interface_mesh_set.cp311-win_amd64.pyd
LightWave2D/binary/interface_mesh_set.cp312-win_amd64.pyd
LightWave2D/binary/interface_simulator.cp310-win_amd64.pyd
LightWave2D/binary/interface_simulator.cp311-win_amd64.pyd
LightWave2D/binary/interface_simulator.cp312-win_amd64.pyd
LightWave2D/binary/interface_source.cp310-win_amd64.pyd
LightWave2D/binary/interface_source.cp311-win_amd64.pyd
LightWave2D/binary/interface_source.cp312-win_amd64.pyd
LightWave2D/binary/libcpp_config.a
LightWave2D/binary/libcpp_field_set.a
LightWave2D/binary/libcpp_mesh_set.a
LightWave2D/binary/libcpp_simulator.a
LightWave2D/binary/libcpp_source.a
LightWave2D/components.py
LightWave2D/detector.py
LightWave2D/directories.py
LightWave2D/experiment.py
LightWave2D/grid.py
LightWave2D/helper.py
LightWave2D/physics.py
LightWave2D/pml.py
LightWave2D/source.py
LightWave2D/utils.py
lightwave2d-0.5.1.dist-info/METADATA
lightwave2d-0.5.1.dist-info/WHEEL
lightwave2d-0.5.1.dist-info/licenses/LICENSE
lightwave2d-0.5.1.dist-info/RECORD
