Metadata-Version: 2.2
Name: LightWave2D
Version: 0.5.1
Summary: A package for finite-difference time domain computation for light propagation
Keywords: FDTD,Light,propagation,physics
Author-Email: Martin Poinsinet de Sivry-Houle <martin.poinsinet.de.sivry@gmail.com>
Classifier: Programming Language :: Python
Classifier: Programming Language :: Python :: 3
Classifier: Programming Language :: Python :: 3.10
Classifier: Programming Language :: Python :: 3.11
Classifier: Programming Language :: Python :: 3.12
Classifier: Programming Language :: Python :: Implementation :: CPython
Classifier: Development Status :: 3 - Alpha
Classifier: Intended Audience :: Science/Research
Classifier: Intended Audience :: Developers
Classifier: Topic :: Scientific/Engineering :: Physics
Classifier: Topic :: Scientific/Engineering :: Mathematics
Classifier: Topic :: Scientific/Engineering :: Visualization
Classifier: Topic :: Software Development :: Libraries :: Python Modules
Classifier: License :: OSI Approved :: MIT License
Classifier: Operating System :: OS Independent
Classifier: Framework :: Jupyter
Classifier: Framework :: Sphinx
Project-URL: Documentation, https://martinpdes.github.io/LightWave2D/
Project-URL: Repository, https://github.com/MartinPdeS/LightWave2D
Requires-Python: >=3.10
Requires-Dist: setuptools_scm[toml]<10,>=8
Requires-Dist: MPSPlots
Requires-Dist: shapely~=2.0
Requires-Dist: numpy==2.2.6
Requires-Dist: opencv-python~=4.10
Requires-Dist: pydantic<2.12.0,>=2.9.2
Requires-Dist: ffmpeg~=1.4
Requires-Dist: pint>=0.24
Requires-Dist: TypedUnit
Provides-Extra: testing
Requires-Dist: pytest>=0.6; extra == "testing"
Requires-Dist: pytest-cov>=2.0; extra == "testing"
Requires-Dist: pytest-json-report==1.5.0; extra == "testing"
Requires-Dist: coverage==7.10.4; extra == "testing"
Provides-Extra: documentation
Requires-Dist: numpydoc==1.9.0; extra == "documentation"
Requires-Dist: sphinx>=5.1.1; extra == "documentation"
Requires-Dist: sphinx-rtd-theme==3.0.2; extra == "documentation"
Requires-Dist: sphinx-gallery==0.19.0; extra == "documentation"
Requires-Dist: pydata-sphinx-theme==0.16.1; extra == "documentation"
Provides-Extra: dev
Requires-Dist: flake8==7.3.0; extra == "dev"
